brd_client/__init__.py
brd_client/example.py
brd_client/scripts.py
brd_client/scraper_api/__init__.py
brd_client/scraper_api/core.py
brd_client/scraper_api/e_commerce/__init__.py
brd_client/scraper_api/e_commerce/amazon.py
brd_client/scraper_api/social_media/__init__.py
brd_client/scraper_api/social_media/facebook.py
brd_client/scraper_api/social_media/instagram.py
brd_client/scraper_api/social_media/reddit.py
brd_client/scraper_api/social_media/tiktok.py
brd_client/scraper_api/social_media/twitter.py
brd_client/scraper_api/social_media/youtube.py
brd_client/serp/__init__.py
brd_client/serp/core.py
brd_client/serp/google.py
brd_client/serp/google_schema_example.py
brd_client-2024.12.1.dist-info/METADATA
brd_client-2024.12.1.dist-info/WHEEL
brd_client-2024.12.1.dist-info/entry_points.txt
brd_client-2024.12.1.dist-info/top_level.txt
brd_client-2024.12.1.dist-info/RECORD
