Metadata-Version: 2.1
Name: brd_client
Version: 2024.12.1
Author: Woojin Cho
Author-email: w.cho@cj.net
License: MIT License
Requires-Python: >=3.9
Requires-Dist: aiohttp
Requires-Dist: click
Requires-Dist: orjson
Requires-Dist: pydantic==1.10
